{"paths":{},"types":[],"uuids":["2dJoYO3+JEuKX87aEWqKQO","d2UF05wGFLo6d7qg6OFB2V","14G1+h95BFAKrV+kUC0IA6","09q7wNmCtPeqfnSBAoFRK+","1bXY9yawpFAZjk5d5mqNtq","21r1gpI3tJS4IhgCX8N4KM","22PKcagipEVqa7i9UxJZnR","c9IutwiQtFea2Mz45A9KGj","16jMj7uHxAZb77hUmAzPMf","56fc2Ai/RFNYpaMT8crweK","71VhFCTINJM6/Ky3oX9nBT","ab19zUlVhFMI2bTMZpOrG4","ecpdLyjvZBwrvm+cedCcQy","1111BjnKFNz7ElXANAaKA3","9djnzw9NxGMJ2eeE1p/tBK","7a/QZLET9IDreTiBfRn2PD","50KTeLfBZDtqqxQZRWMjGx","62ILOAsodO8KrE8w6qPVKL","2ftYY+t6JK+ZKB2kN521Ln","a0yypd+cFA97ie6C3uJWKy","e7q6FL+VZEgLJUjVeDLic/","29FYIk+N1GYaeWH/q1NxQO","15WOfhWTBFDqgzLJor9NPi"],"scenes":{"db://assets/Loading/scenes/Loading.fire":0},"redirect":[12,0,15,0],"deps":["internal"],"packs":{"09d9fd633":[13,2,22,21,0,18,16,17,14,19,1,20],"03cd3bf90":[3,8,4,5,6,9,10,11,7]},"name":"main","importBase":"import","nativeBase":"native","debug":false,"isZip":false,"encrypted":false,"versions":{"import":["03cd3bf90","e3c82","09d9fd633","3534e"],"native":[3,"0df35",2,"bd5dd",8,"17288",4,"247a0",5,"56a8c",6,"e8b12",9,"5f1d9",10,"c06a9",11,"ef16e",7,"6fe21",1,"7ac04"]}}