{"BaiCao":{"hash":"2aaa4","url":"https://kohtut.dev/assets/BaiCao"},"BauCua":{"hash":"4d45b","url":"https://kohtut.dev/assets/BauCua"},"CaoThap":{"hash":"ab168","url":"https://kohtut.dev/assets/CaoThap"},"BaCay":{"hash":"23b83","url":"https://kohtut.dev/assets/BaCay"},"Lieng":{"hash":"22a6f","url":"https://kohtut.dev/assets/Lieng"},"Lobby":{"hash":"117a8","url":"https://kohtut.dev/assets/Lobby"},"Loto":{"hash":"0f16d","url":"https://kohtut.dev/assets/Loto"},"MauBinh":{"hash":"6547e","url":"https://kohtut.dev/assets/MauBinh"},"MiniPoker":{"hash":"7b89a","url":"https://kohtut.dev/assets/MiniPoker"},"OanTuTi":{"hash":"9107a","url":"https://kohtut.dev/assets/OanTuTi"},"Poker":{"hash":"17e95","url":"https://kohtut.dev/assets/Poker"},"Sam":{"hash":"dfe8b","url":"https://kohtut.dev/assets/Sam"},"ShootFish":{"hash":"8afe6","url":"https://kohtut.dev/assets/ShootFish"},"Slot1":{"hash":"836b4","url":"https://kohtut.dev/assets/Slot1"},"Slot10":{"hash":"801f8","url":"https://kohtut.dev/assets/Slot10"},"Slot11Bikini":{"hash":"e2d45","url":"https://kohtut.dev/assets/Slot11Bikini"},"Slot3":{"hash":"9d864","url":"https://kohtut.dev/assets/Slot3"},"Slot3x3":{"hash":"b15b2","url":"https://kohtut.dev/assets/Slot3x3"},"Slot3x3Gem":{"hash":"d7a31","url":"https://kohtut.dev/assets/Slot3x3Gem"},"Slot4":{"hash":"2670f","url":"https://kohtut.dev/assets/Slot4"},"Slot6":{"hash":"8d886","url":"https://kohtut.dev/assets/Slot6"},"Slot7":{"hash":"4d731","url":"https://kohtut.dev/assets/Slot7"},"Slot8":{"hash":"f4853","url":"https://kohtut.dev/assets/Slot8"},"TaiXiuDouble":{"hash":"4f56d","url":"https://kohtut.dev/assets/TaiXiuDouble"},"TaiXiuMD5":{"hash":"473d6","url":"https://kohtut.dev/assets/TaiXiuMD5"},"TaiXiuSieuToc":{"hash":"c5434","url":"https://kohtut.dev/assets/TaiXiuSieuToc"},"TienLen":{"hash":"34413","url":"https://kohtut.dev/assets/TienLen"},"XocDia":{"hash":"0e308","url":"https://kohtut.dev/assets/XocDia"},"internal":{"hash":"01588","url":"https://kohtut.dev/assets/internal"},"main":{"hash":"a7c3b","url":"https://kohtut.dev/assets/main"},"resources":{"hash":"43314","url":"https://kohtut.dev/assets/resources"}}