{"BaCay":{"hash":"50878","url":"https://kohtut.dev/assets/BaCay"},"BaiCao":{"hash":"3ad21","url":"https://kohtut.dev/assets/BaiCao"},"BauCua":{"hash":"cae5a","url":"https://kohtut.dev/assets/BauCua"},"CaoThap":{"hash":"cbee1","url":"https://kohtut.dev/assets/CaoThap"},"Lieng":{"hash":"9d649","url":"https://kohtut.dev/assets/Lieng"},"Lobby":{"hash":"44344","url":"https://kohtut.dev/assets/Lobby"},"Loto":{"hash":"6207c","url":"https://kohtut.dev/assets/Loto"},"MauBinh":{"hash":"d85de","url":"https://kohtut.dev/assets/MauBinh"},"MiniPoker":{"hash":"a95ca","url":"https://kohtut.dev/assets/MiniPoker"},"OanTuTi":{"hash":"7fca0","url":"https://kohtut.dev/assets/OanTuTi"},"Poker":{"hash":"6d8a8","url":"https://kohtut.dev/assets/Poker"},"Sam":{"hash":"0e912","url":"https://kohtut.dev/assets/Sam"},"ShootFish":{"hash":"c2003","url":"https://kohtut.dev/assets/ShootFish"},"Slot1":{"hash":"394cf","url":"https://kohtut.dev/assets/Slot1"},"Slot10":{"hash":"29348","url":"https://kohtut.dev/assets/Slot10"},"Slot11Bikini":{"hash":"bc32b","url":"https://kohtut.dev/assets/Slot11Bikini"},"Slot3":{"hash":"ad245","url":"https://kohtut.dev/assets/Slot3"},"Slot3x3":{"hash":"3281c","url":"https://kohtut.dev/assets/Slot3x3"},"Slot3x3Gem":{"hash":"13efc","url":"https://kohtut.dev/assets/Slot3x3Gem"},"Slot4":{"hash":"c3471","url":"https://kohtut.dev/assets/Slot4"},"Slot6":{"hash":"39669","url":"https://kohtut.dev/assets/Slot6"},"Slot7":{"hash":"2057c","url":"https://kohtut.dev/assets/Slot7"},"Slot8":{"hash":"285b1","url":"https://kohtut.dev/assets/Slot8"},"TaiXiuDouble":{"hash":"3cd0b","url":"https://kohtut.dev/assets/TaiXiuDouble"},"TaiXiuMD5":{"hash":"4a479","url":"https://kohtut.dev/assets/TaiXiuMD5"},"TaiXiuSieuToc":{"hash":"a14fb","url":"https://kohtut.dev/assets/TaiXiuSieuToc"},"TienLen":{"hash":"77cd3","url":"https://kohtut.dev/assets/TienLen"},"XocDia":{"hash":"4d1a3","url":"https://kohtut.dev/assets/XocDia"},"internal":{"hash":"01588","url":"https://kohtut.dev/assets/internal"},"main":{"hash":"65c30","url":"https://kohtut.dev/assets/main"},"resources":{"hash":"b1c23","url":"https://kohtut.dev/assets/resources"}}